[
  {
    "id": 1,
    "name": "rrr",
    "email": "rehammaeeshrraal8@gmail.com",
    "password": "LAHSAMMAH45XYZ123"
  },
  {
    "id": 2,
    "name": "rere",
    "email": "reham@gmail.com",
    "password": "LAHSMAMAHERXYZ123"
  },
  {
    "id": 3,
    "name": "reree",
    "email": "reree@gmail.com",
    "password": "LAHSAMMAHERXYZ123"
  },
  {
    "id": 4,
    "name": "rehaam",
    "email": "rehamm@gmail.com",
    "password": "LAHSAMMAHERXYZ123"
  },
  {
    "id": 5,
    "name": "dd",
    "email": "rereed@gmail.com",
    "password": "RRRRRRRRRRRRRRRRRRRRRRRRRXYZ123"
  },
  {
    "id": 6,
    "name": "xx",
    "email": "rxxxxxr@gamil.com",
    "password": "WWWWWWWWWWWWWWWWXYZ123"
  },
  {
    "id": 7,
    "name": "xx",
    "email": "ssssddss@gmail.com",
    "password": "XXOIUZTREWQXYZ123"
  },
  {
    "id": 8,
    "name": "PetsLover",
    "email": "rereddddddd@gmail.com",
    "password": "DDDDDDDDDDDDDDDDDDDDDDDDDDXYZ123"
  },
  {
    "id": 9,
    "name": "xx",
    "email": "ddddddddddd@gmail.com",
    "password": "DDDDDDDDDDDDDDDDDDDDDDDDDXYZ123"
  },
  {
    "id": 10,
    "name": "dddddddd",
    "email": "rereeddddd@gmail.com",
    "password": "DDDDDDDDDDDDDDDDDDDDDDDDDDXYZ123"
  },
  {
    "id": 11,
    "name": "ccxc",
    "email": "rrddddddd@gamil.com",
    "password": "DDDDDDDDDDDDDDDDDDDDDDDDDDDDDDDDDDXYZ123"
  },
  {
    "id": 12,
    "name": "dddddddd",
    "email": "rrddddd@gamil.com",
    "password": "CCCCCCCCCCCCCCCCCCCCCCCCCCCCCCCXYZ123"
  },
  {
    "id": 13,
    "name": "rrrrrrrrrrrrrrrrr",
    "email": "reredddddded@gmail.com",
    "password": "SSSSSSSSSSSSSSSSSSSSSSSSXYZ123"
  },
  {
    "id": 14,
    "name": "ddddddd",
    "email": "rereddd2@gmail.com",
    "password": "OOOOOOOOOOOOOOOOOOOOOOOOOOXYZ123"
  }
]